base_convert_cli-1.0.3.data/scripts/bs
baseconvertcli/__init__.py
base_convert_cli-1.0.3.dist-info/LICENSE.txt
base_convert_cli-1.0.3.dist-info/METADATA
base_convert_cli-1.0.3.dist-info/WHEEL
base_convert_cli-1.0.3.dist-info/top_level.txt
base_convert_cli-1.0.3.dist-info/RECORD
