Metadata-Version: 2.1
Name: base-convert-cli
Version: 1.0.3
Summary: A CLI tool that converts numbers between bases.
Home-page: https://github.com/Kevinpgalligan/bs
Author: Kevin Galligan
Author-email: galligankevinp@gmail.com
License: UNKNOWN
Platform: UNKNOWN
Classifier: Programming Language :: Python :: 3
Classifier: License :: OSI Approved :: MIT License
License-File: LICENSE.txt
